django_admin_query_executor/__init__.py
django_admin_query_executor/mixins.py
django_admin_query_executor/static/admin/css/query_executor_dark_mode.css
django_admin_query_executor/templates/admin/query_executor_change_list.html
django_admin_query_executor-1.1.0.dist-info/licenses/LICENSE
django_admin_query_executor-1.1.0.dist-info/METADATA
django_admin_query_executor-1.1.0.dist-info/WHEEL
django_admin_query_executor-1.1.0.dist-info/top_level.txt
django_admin_query_executor-1.1.0.dist-info/RECORD
